[{
    "text": "Order ID", "items": [
        { "text": "Filter", "icon": "filter-sm" },
        { "text": "Sort Ascending", "icon": "sort-asc-sm" },
        { "text": "Sort Descending", "icon": "sort-desc-sm" }]
}, {
    "text": "Ship Country", "items": [
        { "text": "Filter", "icon": "filter-sm" },
        { "text": "Sort Ascending", "icon": "sort-asc-sm" },
        { "text": "Sort Descending", "icon": "sort-desc-sm" }]
}, {
    "text": "Ship Address", "items": [
        { "text": "Filter", "icon": "filter-sm" },
        { "text": "Sort Ascending", "icon": "sort-asc-sm" },
        { "text": "Sort Descending", "icon": "sort-desc-sm" }]
}]
